face_recognizer/__init__.py
face_recognizer-0.0.1.dist-info/DESCRIPTION.rst
face_recognizer-0.0.1.dist-info/METADATA
face_recognizer-0.0.1.dist-info/RECORD
face_recognizer-0.0.1.dist-info/WHEEL
face_recognizer-0.0.1.dist-info/metadata.json
face_recognizer-0.0.1.dist-info/top_level.txt
