Metadata-Version: 2.0
Name: face-recognizer
Version: 0.0.1
Summary: Required to be changed
Home-page: https://github.com/pypa/sampleproject
Author: Bei Zhou
Author-email: best.face.recognizer@gmail.com
License: UNKNOWN
Platform: UNKNOWN
Classifier: Programming Language :: Python :: 3
Classifier: License :: OSI Approved :: MIT License
Classifier: Operating System :: OS Independent
